MANIFEST.in
README
README.rst
setup.cfg
setup.py
pypirc/__init__.py
pypirc/cmd.py
pypirc/pypirc.py
pypirc.egg-info/PKG-INFO
pypirc.egg-info/SOURCES.txt
pypirc.egg-info/dependency_links.txt
pypirc.egg-info/entry_points.txt
pypirc.egg-info/top_level.txt