Metadata-Version: 1.0
Name: pypirc
Version: 1.0.3
Summary: PyPiRC: .pypirc Manager
Home-page: https://github.com/ampledata/pypirc
Author: Greg Albrecht
Author-email: gba@splunk.com
License: Apache License 2.0
Platform: UNKNOWN
